undetected_browser_tool/__init__.py
undetected_browser_tool/undetected_browser.py
undetected_browser_tool-1.1.3.dist-info/LICENSE.txt
undetected_browser_tool-1.1.3.dist-info/METADATA
undetected_browser_tool-1.1.3.dist-info/WHEEL
undetected_browser_tool-1.1.3.dist-info/RECORD
