Metadata-Version: 2.3
Name: undetected-browser-tool
Version: 1.1.3
Summary: A langchain tool implementation of Undetected with Selenium and Chrome for page fetching, making it easier to bypass bot detectors
License: MIT
Keywords: AI,Agents,langchain,undetected,selenium,chrome,browser,bot,detection,bypass
Author: patrick o'leary
Author-email: pjaol@pjaol.com
Requires-Python: >=3.9,<4.0
Classifier: License :: OSI Approved :: MIT License
Classifier: Programming Language :: Python :: 3
Classifier: Programming Language :: Python :: 3.9
Classifier: Programming Language :: Python :: 3.10
Classifier: Programming Language :: Python :: 3.11
Classifier: Programming Language :: Python :: 3.12
Classifier: Programming Language :: Python :: 3.13
Classifier: Topic :: Internet :: WWW/HTTP :: Browsers
Classifier: Topic :: Scientific/Engineering :: Artificial Intelligence
Classifier: Topic :: Scientific/Engineering :: Information Analysis
Requires-Dist: langchain (>=0.3.19,<0.4.0)
Requires-Dist: langchain-core (>=0.3.37,<0.4.0)
Requires-Dist: selenium (>=4.23.1,<5.0.0)
Requires-Dist: undetected-chromedriver (>=3.5.5,<4.0.0)
Requires-Dist: webdriver-manager (>=4.0.2,<5.0.0)
Project-URL: Homepage, https://github.com/thevgergroup/undetected-browser-tool
Project-URL: Repository, https://github.com/thevgergroup/undetected-browser-tool.git
